jatayu/__init__.py
jatayu/app.py
jatayu/compat.py
jatayu/database.py
jatayu/extensions.py
jatayu/settings.py
jatayu/utils.py
jatayu/orm/__init__.py
jatayu/orm/fields.py
jatayu/orm/init.py
jatayu/orm/postgresql.py
jatayu/public/__init__.py
jatayu/public/forms.py
jatayu/public/views.py
jatayu/user/__init__.py
jatayu/user/forms.py
jatayu/user/models.py
jatayu/user/views.py
tests/__init__.py
tests/conftest.py
tests/factories.py
tests/settings.py
tests/test_forms.py
tests/test_functional.py
tests/test_models.py
jatayu-0.1.0.dist-info/LICENSE
jatayu-0.1.0.dist-info/METADATA
jatayu-0.1.0.dist-info/WHEEL
jatayu-0.1.0.dist-info/top_level.txt
jatayu-0.1.0.dist-info/RECORD
