Metadata-Version: 2.1
Name: jatayu
Version: 0.1.0
Summary: Identity & Access Management with Python, asyncio & dataclasses
Home-page: https://github.com/reckonsys/jatayu
Author: Reckonsys
Author-email: techwork@reckonsys.com
License: MIT
Keywords: jatayu reckonsys iam user management ldap kerberos
Platform: UNKNOWN
Classifier: Development Status :: 4 - Beta
Classifier: Intended Audience :: Developers
Classifier: Topic :: Software Development :: Build Tools
Classifier: License :: OSI Approved :: MIT License
Classifier: Programming Language :: Python :: 3
Classifier: Programming Language :: Python :: 3.7
